<?xml version = '1.0' encoding = 'UTF-8'?>
<FKIndexAssociation class="oracle.dbtools.crest.model.design.relational.FKIndexAssociation" directorySegmentName="seg_0" id="70E1774A-7166-5C8C-18AC-8C79C7E3D4DF" containerWithKeyObject="ABA4AE0D-4CD3-02BD-9C36-A142BBC4BD90" localFKIndex="46D530A8-5254-753C-1179-6E04F0A7E078" name="TBL_GIST_USUARIOS_FK">
<createdBy>Lalos</createdBy>
<createdTime>2024-02-22 19:50:52 UTC</createdTime>
<ownerDesignName>GITHUB</ownerDesignName>
<referredTableLongName>USUARIOS</referredTableLongName>
<deleteRule>NO ACTION</deleteRule>
<referredTableID>802222FD-7BE4-8A5E-0AC2-D2AE8947D3B1</referredTableID>
<keyObject>79E4B218-874C-F700-D35A-2E9C72D6DF03</keyObject>
<referredKeyID>79E4B218-874C-F700-D35A-2E9C72D6DF03</referredKeyID>
<mandatory>true</mandatory>
<refColNames>ID_USUARIO</refColNames>
<transferable>true</transferable>
<rely>false</rely>
<columnDependencyConstraintGenerateInDDL>true</columnDependencyConstraintGenerateInDDL>
</FKIndexAssociation>
